genepy3d/__init__.py
genepy3d/io/__init__.py
genepy3d/io/base.py
genepy3d/io/catmaid.py
genepy3d/io/swc.py
genepy3d/io/trackmate.py
genepy3d/obj/__init__.py
genepy3d/obj/curves.py
genepy3d/obj/points.py
genepy3d/obj/surfaces.py
genepy3d/obj/trees.py
genepy3d/objext/__init__.py
genepy3d/objext/simpletracks.py
genepy3d/util/__init__.py
genepy3d/util/geo.py
genepy3d/util/plot.py
genepy3d/util/signal.py
genepy3d-0.3.4.dist-info/LICENSE
genepy3d-0.3.4.dist-info/METADATA
genepy3d-0.3.4.dist-info/WHEEL
genepy3d-0.3.4.dist-info/top_level.txt
genepy3d-0.3.4.dist-info/RECORD
