Metadata-Version: 2.1
Name: genepy3d
Version: 0.3.4
Summary: Python Library for 3D Quantitative Geometry in Computation Microscopy
Home-page: https://gitlab.com/genepy3d/genepy3d
Author: genepy3d-team
License: BSD-3-Clause
Classifier: License :: OSI Approved :: BSD License
Classifier: Programming Language :: Python :: 3
Classifier: Programming Language :: Python :: 3.9
Requires-Python: >=3.9
License-File: LICENSE
Requires-Dist: anytree>=2.8.0
Requires-Dist: matplotlib>=3.3.4
Requires-Dist: numpy<2,>=1.21
Requires-Dist: numpy-stl>=2.17.1
Requires-Dist: pathos>=0.2.8
Requires-Dist: pandas>=1.3.0
Requires-Dist: pot>=0.8.2
Requires-Dist: pynrrd>=0.4.3
Requires-Dist: pyevtk>=1.5.0
Requires-Dist: pillow>=8.4.0
Requires-Dist: PyAstronomy>=0.18.0
Requires-Dist: requests>=2.27.1
Requires-Dist: scikit-learn>=0.24.2
Requires-Dist: scikit-image>=0.19.1
Requires-Dist: seaborn>=0.11.2
Requires-Dist: tables>=3.7.0
Requires-Dist: trimesh>=3.14.1
Requires-Dist: vtk>=9.1.0
Requires-Dist: alphashape>=1.3.1
Requires-Dist: h5py>=3.11.0
